{"directed": true, "graph": {}, "nodes": [{"born": 12.75, "id": 0, "contents": [0]}, {"born": 12.75, "id": 1, "contents": [1]}, {"born": 12.75, "id": 2, "contents": [2]}, {"born": 12.75, "id": 3, "contents": [3]}, {"born": 12.75, "id": 4, "contents": [4]}, {"born": 12.75, "id": 5, "contents": [5]}, {"born": 12.75, "id": 6, "contents": [6]}, {"born": 12.75, "id": 7, "contents": [7]}, {"born": 12.75, "id": 8, "contents": [8]}, {"born": 12.75, "id": 9, "contents": [9]}, {"born": 12.75, "id": 10, "contents": [10]}, {"born": 12.75, "id": 11, "contents": [11]}, {"born": 12.75, "id": 12, "contents": [12]}, {"born": 12.75, "id": 13, "contents": [13]}, {"born": 12.75, "id": 14, "contents": [14]}, {"born": 12.75, "id": 15, "contents": [15]}, {"born": 12.75, "id": 16, "contents": [16]}, {"born": 12.75, "id": 17, "contents": [17]}, {"born": 12.75, "id": 18, "contents": [18]}, {"born": 12.75, "id": 19, "contents": [19]}, {"born": 12.75, "id": 20, "contents": [20]}, {"born": 12.75, "id": 21, "contents": [21]}, {"born": 12.75, "id": 22, "contents": [22]}, {"born": 12.75, "id": 23, "contents": [23]}, {"born": 12.75, "id": 24, "contents": [24]}, {"born": 12.75, "id": 25, "contents": [25]}, {"born": 12.75, "id": 26, "contents": [26]}, {"born": 12.75, "id": 27, "contents": [27]}, {"born": 12.75, "id": 28, "contents": [28]}, {"born": 12.75, "id": 29, "contents": [29]}, {"born": 12.75, "id": 30, "contents": [30]}, {"born": 12.75, "id": 31, "contents": [31]}, {"born": 12.75, "id": 32, "contents": [32]}, {"born": 12.75, "id": 33, "contents": [33]}, {"born": 12.75, "id": 34, "contents": [34]}, {"born": 12.75, "id": 35, "contents": [35]}, {"born": 12.75, "id": 36, "contents": [36]}, {"born": 12.75, "id": 37, "contents": [37]}, {"born": 12.75, "id": 38, "contents": [38]}, {"born": 12.75, "id": 39, "contents": [39]}, {"born": 12.75, "id": 40, "contents": [40]}, {"born": 12.75, "id": 41, "contents": [41]}, {"born": 12.75, "id": 42, "contents": [42]}, {"born": 12.75, "id": 43, "contents": [43]}, {"born": 12.75, "id": 44, "contents": [44]}, {"born": 12.75, "id": 45, "contents": [45]}, {"born": 12.75, "id": 46, "contents": [46]}, {"born": 12.75, "id": 47, "contents": [47]}, {"born": 12.75, "id": 48, "contents": [48]}, {"born": 12.75, "id": 49, "contents": [49]}, {"born": 12.75, "id": 50, "contents": [50]}, {"born": 12.75, "id": 51, "contents": [51]}, {"born": 12.75, "id": 52, "contents": [52]}, {"born": 12.75, "id": 53, "contents": [53]}, {"born": 12.75, "id": 54, "contents": [54]}, {"born": 12.75, "id": 55, "contents": [55]}, {"born": 12.75, "id": 56, "contents": [56]}, {"born": 12.75, "id": 57, "contents": [57]}, {"born": 12.75, "id": 58, "contents": [58]}, {"born": 12.75, "id": 59, "contents": [59]}, {"born": 12.75, "id": 60, "contents": [60]}, {"born": 12.75, "id": 61, "contents": [61]}, {"born": 12.75, "id": 62, "contents": [62]}, {"born": 12.75, "id": 63, "contents": [63]}, {"born": 12.75, "id": 64, "contents": [64]}, {"born": 12.75, "id": 65, "contents": [65]}, {"born": 12.75, "id": 66, "contents": [66]}, {"born": 12.75, "id": 67, "contents": [67]}, {"born": 12.75, "id": 68, "contents": [68]}, {"born": 12.75, "id": 69, "contents": [69]}, {"born": 12.75, "id": 70, "contents": [70]}, {"born": 12.75, "id": 71, "contents": [71]}, {"born": 12.75, "id": 72, "contents": [72]}, {"born": 12.75, "id": 73, "contents": [73]}, {"born": 12.75, "id": 74, "contents": [74]}, {"born": 12.75, "id": 75, "contents": [75]}, {"born": 12.75, "id": 76, "contents": [76]}, {"born": 12.75, "id": 77, "contents": [77]}, {"born": 12.75, "id": 78, "contents": [78]}, {"born": 12.75, "id": 79, "contents": [79]}, {"born": 12.75, "id": 80, "contents": [80]}, {"born": 12.75, "id": 81, "contents": [81]}, {"born": 12.75, "id": 82, "contents": [82]}, {"born": 12.75, "id": 83, "contents": [83]}, {"born": 12.75, "id": 84, "contents": [84]}, {"born": 12.75, "id": 85, "contents": [85]}, {"born": 12.73725, "id": 86, "contents": [0, 1, 20]}, {"born": 12.73725, "id": 87, "contents": [4, 11, 14]}, {"born": 12.73725, "id": 88, "contents": [5, 7, 10, 40, 41, 42]}, {"born": 12.73725, "id": 89, "contents": [6, 15]}, {"born": 12.73725, "id": 90, "contents": [9, 12, 21]}, {"born": 12.73725, "id": 91, "contents": [17, 18, 22]}, {"born": 12.73725, "id": 92, "contents": [32, 35]}, {"born": 12.73725, "id": 93, "contents": [43, 44, 63]}, {"born": 12.73725, "id": 94, "contents": [47, 54, 57]}, {"born": 12.73725, "id": 95, "contents": [48, 50, 53, 83, 84, 85]}, {"born": 12.73725, "id": 96, "contents": [49, 58]}, {"born": 12.73725, "id": 97, "contents": [52, 55, 64]}, {"born": 12.73725, "id": 98, "contents": [60, 61, 65]}, {"born": 12.73725, "id": 99, "contents": [75, 78]}, {"born": 12.3165, "id": 100, "contents": [3, 31]}, {"born": 12.3165, "id": 101, "contents": [46, 74]}, {"born": 11.258249999999999, "id": 102, "contents": [0, 1, 19, 20]}, {"born": 11.258249999999999, "id": 103, "contents": [43, 44, 62, 63]}, {"born": 10.72275, "id": 104, "contents": [9, 12, 13, 21]}, {"born": 10.72275, "id": 105, "contents": [52, 55, 56, 64]}, {"born": 9.8685, "id": 106, "contents": [2, 3, 31]}, {"born": 9.8685, "id": 107, "contents": [45, 46, 74]}, {"born": 9.231, "id": 108, "contents": [2, 3, 8, 31]}, {"born": 9.231, "id": 109, "contents": [45, 46, 51, 74]}, {"born": 9.18, "id": 110, "contents": [4, 9, 11, 12, 13, 14, 21]}, {"born": 9.18, "id": 111, "contents": [47, 52, 54, 55, 56, 57, 64]}, {"born": 8.91225, "id": 112, "contents": [0, 1, 4, 9, 11, 12, 13, 14, 19, 20, 21]}, {"born": 8.91225, "id": 113, "contents": [43, 44, 47, 52, 54, 55, 56, 57, 62, 63, 64]}, {"born": 7.203749999999999, "id": 114, "contents": [0, 1, 4, 9, 11, 12, 13, 14, 19, 20, 21, 43, 44, 47, 52, 54, 55, 56, 57, 62, 63, 64]}, {"born": 7.1145, "id": 115, "contents": [16, 17, 18, 22]}, {"born": 7.1145, "id": 116, "contents": [59, 60, 61, 65]}, {"born": 5.9925, "id": 117, "contents": [32, 34, 35]}, {"born": 5.9925, "id": 118, "contents": [75, 77, 78]}, {"born": 4.972499999999999, "id": 119, "contents": [37, 39]}, {"born": 4.972499999999999, "id": 120, "contents": [80, 82]}, {"born": 4.59, "id": 121, "contents": [25, 26]}, {"born": 4.59, "id": 122, "contents": [68, 69]}, {"born": 4.436999999999999, "id": 123, "contents": [2, 3, 8, 31, 32, 34, 35]}, {"born": 4.436999999999999, "id": 124, "contents": [45, 46, 51, 74, 75, 77, 78]}, {"born": 4.14375, "id": 125, "contents": [2, 3, 8, 30, 31, 32, 34, 35]}, {"born": 4.14375, "id": 126, "contents": [45, 46, 51, 73, 74, 75, 77, 78]}, {"born": 4.0417499999999995, "id": 127, "contents": [36, 37, 39]}, {"born": 4.0417499999999995, "id": 128, "contents": [79, 80, 82]}, {"born": 3.7612499999999995, "id": 129, "contents": [24, 25, 26]}, {"born": 3.7612499999999995, "id": 130, "contents": [67, 68, 69]}, {"born": 3.73575, "id": 131, "contents": [36, 37, 38, 39]}, {"born": 3.73575, "id": 132, "contents": [79, 80, 81, 82]}, {"born": 3.6975, "id": 133, "contents": [23, 29]}, {"born": 3.6975, "id": 134, "contents": [66, 72]}, {"born": 3.468, "id": 135, "contents": [2, 3, 8, 30, 31, 32, 33, 34, 35]}, {"born": 3.468, "id": 136, "contents": [45, 46, 51, 73, 74, 75, 76, 77, 78]}, {"born": 3.32775, "id": 137, "contents": [27, 28]}, {"born": 3.32775, "id": 138, "contents": [70, 71]}, {"born": 3.1875, "id": 139, "contents": [24, 25, 26, 27, 28]}, {"born": 3.1875, "id": 140, "contents": [67, 68, 69, 70, 71]}, {"born": 2.69025, "id": 141, "contents": [5, 7, 10, 36, 37, 38, 39, 40, 41, 42]}, {"born": 2.69025, "id": 142, "contents": [48, 50, 53, 79, 80, 81, 82, 83, 84, 85]}, {"born": 2.601, "id": 143, "contents": [23, 24, 25, 26, 27, 28, 29]}, {"born": 2.601, "id": 144, "contents": [66, 67, 68, 69, 70, 71, 72]}, {"born": 2.5117499999999997, "id": 145, "contents": [6, 15, 16, 17, 18, 22]}, {"born": 2.5117499999999997, "id": 146, "contents": [49, 58, 59, 60, 61, 65]}, {"born": 2.3842499999999998, "id": 147, "contents": [0, 1, 4, 6, 9, 11, 12, 13, 14, 15, 16, 17, 18, 19, 20, 21, 22, 43, 44, 47, 52, 54, 55, 56, 57, 62, 63, 64]}, {"born": 1.3005, "id": 148, "contents": [2, 3, 8, 23, 24, 25, 26, 27, 28, 29, 30, 31, 32, 33, 34, 35]}, {"born": 1.3005, "id": 149, "contents": [45, 46, 51, 66, 67, 68, 69, 70, 71, 72, 73, 74, 75, 76, 77, 78]}, {"born": 0.9562499999999999, "id": 150, "contents": [2, 3, 5, 7, 8, 10, 23, 24, 25, 26, 27, 28, 29, 30, 31, 32, 33, 34, 35, 36, 37, 38, 39, 40, 41, 42]}, {"born": 0.9562499999999999, "id": 151, "contents": [45, 46, 48, 50, 51, 53, 66, 67, 68, 69, 70, 71, 72, 73, 74, 75, 76, 77, 78, 79, 80, 81, 82, 83, 84, 85]}, {"born": 0.0, "id": 152, "contents": [0, 1, 2, 3, 4, 5, 6, 7, 8, 9, 10, 11, 12, 13, 14, 15, 16, 17, 18, 19, 20, 21, 22, 23, 24, 25, 26, 27, 28, 29, 30, 31, 32, 33, 34, 35, 36, 37, 38, 39, 40, 41, 42, 43, 44, 45, 46, 47, 48, 49, 50, 51, 52, 53, 54, 55, 56, 57, 58, 59, 60, 61, 62, 63, 64, 65, 66, 67, 68, 69, 70, 71, 72, 73, 74, 75, 76, 77, 78, 79, 80, 81, 82, 83, 84, 85]}], "links": [{"source": 0, "length": 0.012750000000000483, "type": "up", "log_p": 0.0, "target": 86}, {"source": 1, "length": 0.012750000000000483, "type": "up", "log_p": 0.0, "target": 86}, {"source": 2, "length": 2.881500000000001, "type": "up", "log_p": 0.0, "target": 106}, {"source": 3, "length": 0.43350000000000044, "type": "up", "log_p": 0.0, "target": 100}, {"source": 4, "length": 0.012750000000000483, "type": "up", "log_p": 0.0, "target": 87}, {"source": 5, "length": 0.012750000000000483, "type": "up", "log_p": 0.0, "target": 88}, {"source": 6, "length": 0.012750000000000483, "type": "up", "log_p": 0.0, "target": 89}, {"source": 7, "length": 0.012750000000000483, "type": "up", "log_p": 0.0, "target": 88}, {"source": 8, "length": 3.519, "type": "up", "log_p": 0.0, "target": 108}, {"source": 9, "length": 0.012750000000000483, "type": "up", "log_p": 0.0, "target": 90}, {"source": 10, "length": 0.012750000000000483, "type": "up", "log_p": 0.0, "target": 88}, {"source": 11, "length": 0.012750000000000483, "type": "up", "log_p": 0.0, "target": 87}, {"source": 12, "length": 0.012750000000000483, "type": "up", "log_p": 0.0, "target": 90}, {"source": 13, "length": 2.0272500000000004, "type": "up", "log_p": 0.0, "target": 104}, {"source": 14, "length": 0.012750000000000483, "type": "up", "log_p": 0.0, "target": 87}, {"source": 15, "length": 0.012750000000000483, "type": "up", "log_p": 0.0, "target": 89}, {"source": 16, "length": 5.6355, "type": "up", "log_p": 0.0, "target": 115}, {"source": 17, "length": 0.012750000000000483, "type": "up", "log_p": 0.0, "target": 91}, {"source": 18, "length": 0.012750000000000483, "type": "up", "log_p": 0.0, "target": 91}, {"source": 19, "length": 1.4917500000000015, "type": "up", "log_p": 0.0, "target": 102}, {"source": 20, "length": 0.012750000000000483, "type": "up", "log_p": 0.0, "target": 86}, {"source": 21, "length": 0.012750000000000483, "type": "up", "log_p": 0.0, "target": 90}, {"source": 22, "length": 0.012750000000000483, "type": "up", "log_p": 0.0, "target": 91}, {"source": 23, "length": 9.0525, "type": "up", "log_p": 0.0, "target": 133}, {"source": 24, "length": 8.98875, "type": "up", "log_p": 0.0, "target": 129}, {"source": 25, "length": 8.16, "type": "up", "log_p": 0.0, "target": 121}, {"source": 26, "length": 8.16, "type": "up", "log_p": 0.0, "target": 121}, {"source": 27, "length": 9.42225, "type": "up", "log_p": 0.0, "target": 137}, {"source": 28, "length": 9.42225, "type": "up", "log_p": 0.0, "target": 137}, {"source": 29, "length": 9.0525, "type": "up", "log_p": 0.0, "target": 133}, {"source": 30, "length": 8.60625, "type": "up", "log_p": 0.0, "target": 125}, {"source": 31, "length": 0.43350000000000044, "type": "up", "log_p": 0.0, "target": 100}, {"source": 32, "length": 0.012750000000000483, "type": "up", "log_p": 0.0, "target": 92}, {"source": 33, "length": 9.282, "type": "up", "log_p": 0.0, "target": 135}, {"source": 34, "length": 6.7575, "type": "up", "log_p": 0.0, "target": 117}, {"source": 35, "length": 0.012750000000000483, "type": "up", "log_p": 0.0, "target": 92}, {"source": 36, "length": 8.70825, "type": "up", "log_p": 0.0, "target": 127}, {"source": 37, "length": 7.777500000000001, "type": "up", "log_p": 0.0, "target": 119}, {"source": 38, "length": 9.01425, "type": "up", "log_p": 0.0, "target": 131}, {"source": 39, "length": 7.777500000000001, "type": "up", "log_p": 0.0, "target": 119}, {"source": 40, "length": 0.012750000000000483, "type": "up", "log_p": 0.0, "target": 88}, {"source": 41, "length": 0.012750000000000483, "type": "up", "log_p": 0.0, "target": 88}, {"source": 42, "length": 0.012750000000000483, "type": "up", "log_p": 0.0, "target": 88}, {"source": 43, "length": 0.012750000000000483, "type": "up", "log_p": 0.0, "target": 93}, {"source": 44, "length": 0.012750000000000483, "type": "up", "log_p": 0.0, "target": 93}, {"source": 45, "length": 2.881500000000001, "type": "up", "log_p": 0.0, "target": 107}, {"source": 46, "length": 0.43350000000000044, "type": "up", "log_p": 0.0, "target": 101}, {"source": 47, "length": 0.012750000000000483, "type": "up", "log_p": 0.0, "target": 94}, {"source": 48, "length": 0.012750000000000483, "type": "up", "log_p": 0.0, "target": 95}, {"source": 49, "length": 0.012750000000000483, "type": "up", "log_p": 0.0, "target": 96}, {"source": 50, "length": 0.012750000000000483, "type": "up", "log_p": 0.0, "target": 95}, {"source": 51, "length": 3.519, "type": "up", "log_p": 0.0, "target": 109}, {"source": 52, "length": 0.012750000000000483, "type": "up", "log_p": 0.0, "target": 97}, {"source": 53, "length": 0.012750000000000483, "type": "up", "log_p": 0.0, "target": 95}, {"source": 54, "length": 0.012750000000000483, "type": "up", "log_p": 0.0, "target": 94}, {"source": 55, "length": 0.012750000000000483, "type": "up", "log_p": 0.0, "target": 97}, {"source": 56, "length": 2.0272500000000004, "type": "up", "log_p": 0.0, "target": 105}, {"source": 57, "length": 0.012750000000000483, "type": "up", "log_p": 0.0, "target": 94}, {"source": 58, "length": 0.012750000000000483, "type": "up", "log_p": 0.0, "target": 96}, {"source": 59, "length": 5.6355, "type": "up", "log_p": 0.0, "target": 116}, {"source": 60, "length": 0.012750000000000483, "type": "up", "log_p": 0.0, "target": 98}, {"source": 61, "length": 0.012750000000000483, "type": "up", "log_p": 0.0, "target": 98}, {"source": 62, "length": 1.4917500000000015, "type": "up", "log_p": 0.0, "target": 103}, {"source": 63, "length": 0.012750000000000483, "type": "up", "log_p": 0.0, "target": 93}, {"source": 64, "length": 0.012750000000000483, "type": "up", "log_p": 0.0, "target": 97}, {"source": 65, "length": 0.012750000000000483, "type": "up", "log_p": 0.0, "target": 98}, {"source": 66, "length": 9.0525, "type": "up", "log_p": 0.0, "target": 134}, {"source": 67, "length": 8.98875, "type": "up", "log_p": 0.0, "target": 130}, {"source": 68, "length": 8.16, "type": "up", "log_p": 0.0, "target": 122}, {"source": 69, "length": 8.16, "type": "up", "log_p": 0.0, "target": 122}, {"source": 70, "length": 9.42225, "type": "up", "log_p": 0.0, "target": 138}, {"source": 71, "length": 9.42225, "type": "up", "log_p": 0.0, "target": 138}, {"source": 72, "length": 9.0525, "type": "up", "log_p": 0.0, "target": 134}, {"source": 73, "length": 8.60625, "type": "up", "log_p": 0.0, "target": 126}, {"source": 74, "length": 0.43350000000000044, "type": "up", "log_p": 0.0, "target": 101}, {"source": 75, "length": 0.012750000000000483, "type": "up", "log_p": 0.0, "target": 99}, {"source": 76, "length": 9.282, "type": "up", "log_p": 0.0, "target": 136}, {"source": 77, "length": 6.7575, "type": "up", "log_p": 0.0, "target": 118}, {"source": 78, "length": 0.012750000000000483, "type": "up", "log_p": 0.0, "target": 99}, {"source": 79, "length": 8.70825, "type": "up", "log_p": 0.0, "target": 128}, {"source": 80, "length": 7.777500000000001, "type": "up", "log_p": 0.0, "target": 120}, {"source": 81, "length": 9.01425, "type": "up", "log_p": 0.0, "target": 132}, {"source": 82, "length": 7.777500000000001, "type": "up", "log_p": 0.0, "target": 120}, {"source": 83, "length": 0.012750000000000483, "type": "up", "log_p": 0.0, "target": 95}, {"source": 84, "length": 0.012750000000000483, "type": "up", "log_p": 0.0, "target": 95}, {"source": 85, "length": 0.012750000000000483, "type": "up", "log_p": 0.0, "target": 95}, {"source": 86, "length": 0.012750000000000483, "type": "down", "log_p": 0.4290521800095386, "target": 0}, {"source": 86, "length": 0.012750000000000483, "type": "down", "log_p": 0.22691291744484726, "target": 1}, {"source": 86, "length": 0.012750000000000483, "type": "down", "log_p": 0.3976577889586126, "target": 20}, {"source": 86, "length": 1.479000000000001, "type": "up", "log_p": 0.0, "target": 102}, {"source": 87, "length": 0.012750000000000483, "type": "down", "log_p": 0.4017277843738286, "target": 11}, {"source": 87, "length": 0.012750000000000483, "type": "down", "log_p": 0.48161226557291603, "target": 4}, {"source": 87, "length": 0.012750000000000483, "type": "down", "log_p": 0.356471844396261, "target": 14}, {"source": 87, "length": 3.55725, "type": "up", "log_p": 0.0, "target": 110}, {"source": 88, "length": 0.012750000000000483, "type": "down", "log_p": 0.5058481866487625, "target": 5}, {"source": 88, "length": 0.012750000000000483, "type": "down", "log_p": 0.5058481866487625, "target": 7}, {"source": 88, "length": 0.012750000000000483, "type": "down", "log_p": 0.35781800936969643, "target": 40}, {"source": 88, "length": 0.012750000000000483, "type": "down", "log_p": 0.47981160221161323, "target": 41}, {"source": 88, "length": 0.012750000000000483, "type": "down", "log_p": 0.509132078595004, "target": 10}, {"source": 88, "length": 10.047, "type": "up", "log_p": 0.04131402862918626, "target": 141}, {"source": 88, "length": 0.012750000000000483, "type": "down", "log_p": 0.4467977600770814, "target": 42}, {"source": 89, "length": 10.2255, "type": "up", "log_p": 0.0, "target": 145}, {"source": 89, "length": 0.012750000000000483, "type": "down", "log_p": 0.4246897770761755, "target": 6}, {"source": 89, "length": 0.012750000000000483, "type": "down", "log_p": 0.36243147018347266, "target": 15}, {"source": 90, "length": 2.0145, "type": "up", "log_p": 0.0, "target": 104}, {"source": 90, "length": 0.012750000000000483, "type": "down", "log_p": 0.3644971351957693, "target": 9}, {"source": 90, "length": 0.012750000000000483, "type": "down", "log_p": 0.35419338808396916, "target": 12}, {"source": 90, "length": 0.012750000000000483, "type": "down", "log_p": 0.37879044187503413, "target": 21}, {"source": 91, "length": 0.012750000000000483, "type": "down", "log_p": 0.28502670633245364, "target": 17}, {"source": 91, "length": 0.012750000000000483, "type": "down", "log_p": 0.26362285911064753, "target": 18}, {"source": 91, "length": 5.62275, "type": "up", "log_p": 0.07728883585920591, "target": 115}, {"source": 91, "length": 0.012750000000000483, "type": "down", "log_p": 0.1178948580462215, "target": 22}, {"source": 92, "length": 0.012750000000000483, "type": "down", "log_p": 0.3384441430529952, "target": 32}, {"source": 92, "length": 0.012750000000000483, "type": "down", "log_p": 0.15543382038060233, "target": 35}, {"source": 92, "length": 6.74475, "type": "up", "log_p": 0.025384057021863318, "target": 117}, {"source": 93, "length": 0.012750000000000483, "type": "down", "log_p": 0.3976577889586126, "target": 63}, {"source": 93, "length": 0.012750000000000483, "type": "down", "log_p": 0.4290521800095386, "target": 43}, {"source": 93, "length": 0.012750000000000483, "type": "down", "log_p": 0.22691291744484726, "target": 44}, {"source": 93, "length": 1.479000000000001, "type": "up", "log_p": 0.0, "target": 103}, {"source": 94, "length": 0.012750000000000483, "type": "down", "log_p": 0.3564720685220748, "target": 57}, {"source": 94, "length": 0.012750000000000483, "type": "down", "log_p": 0.4930297988225615, "target": 47}, {"source": 94, "length": 0.012750000000000483, "type": "down", "log_p": 0.4423411811475122, "target": 54}, {"source": 94, "length": 3.55725, "type": "up", "log_p": 0.005130454664778048, "target": 111}, {"source": 95, "length": 10.047, "type": "up", "log_p": 0.04131219729582078, "target": 142}, {"source": 95, "length": 0.012750000000000483, "type": "down", "log_p": 0.5058481866600748, "target": 48}, {"source": 95, "length": 0.012750000000000483, "type": "down", "log_p": 0.5058481866600748, "target": 50}, {"source": 95, "length": 0.012750000000000483, "type": "down", "log_p": 0.35781800931209196, "target": 83}, {"source": 95, "length": 0.012750000000000483, "type": "down", "log_p": 0.47981160220102415, "target": 84}, {"source": 95, "length": 0.012750000000000483, "type": "down", "log_p": 0.5091320786107201, "target": 53}, {"source": 95, "length": 0.012750000000000483, "type": "down", "log_p": 0.44679776004543825, "target": 85}, {"source": 96, "length": 0.012750000000000483, "type": "down", "log_p": 0.4246897770761753, "target": 49}, {"source": 96, "length": 0.012750000000000483, "type": "down", "log_p": 0.36243147018347277, "target": 58}, {"source": 96, "length": 10.2255, "type": "up", "log_p": 0.0, "target": 146}, {"source": 97, "length": 0.012750000000000483, "type": "down", "log_p": 0.37878274838017933, "target": 64}, {"source": 97, "length": 2.0145, "type": "up", "log_p": 0.027346433635957196, "target": 105}, {"source": 97, "length": 0.012750000000000483, "type": "down", "log_p": 0.42950726727360444, "target": 52}, {"source": 97, "length": 0.012750000000000483, "type": "down", "log_p": 0.42301285509197717, "target": 55}, {"source": 98, "length": 0.012750000000000483, "type": "down", "log_p": 0.11852116327761102, "target": 65}, {"source": 98, "length": 0.012750000000000483, "type": "down", "log_p": 0.1971591676787285, "target": 60}, {"source": 98, "length": 0.012750000000000483, "type": "down", "log_p": 0.17003318546222967, "target": 61}, {"source": 98, "length": 5.62275, "type": "up", "log_p": 0.03613498728187892, "target": 116}, {"source": 99, "length": 0.012750000000000483, "type": "down", "log_p": 0.33844414305299525, "target": 75}, {"source": 99, "length": 0.012750000000000483, "type": "down", "log_p": 0.15543382038060222, "target": 78}, {"source": 99, "length": 6.74475, "type": "up", "log_p": 0.02538405702186342, "target": 118}, {"source": 100, "length": 2.4480000000000004, "type": "up", "log_p": 0.0, "target": 106}, {"source": 100, "length": 0.43350000000000044, "type": "down", "log_p": 0.24306327785852888, "target": 3}, {"source": 100, "length": 0.43350000000000044, "type": "down", "log_p": 0.3436920719502863, "target": 31}, {"source": 101, "length": 0.43350000000000044, "type": "down", "log_p": 0.34369207195028634, "target": 74}, {"source": 101, "length": 2.4480000000000004, "type": "up", "log_p": 0.0, "target": 107}, {"source": 101, "length": 0.43350000000000044, "type": "down", "log_p": 0.24306327785852905, "target": 46}, {"source": 102, "length": 2.3459999999999983, "type": "up", "log_p": 0.09048467890342664, "target": 112}, {"source": 102, "length": 1.4917500000000015, "type": "down", "log_p": 0.2868029485033702, "target": 19}, {"source": 102, "length": 1.479000000000001, "type": "down", "log_p": 0.0, "target": 86}, {"source": 103, "length": 2.3459999999999983, "type": "up", "log_p": 0.08358056547902627, "target": 113}, {"source": 103, "length": 1.479000000000001, "type": "down", "log_p": 0.0, "target": 93}, {"source": 103, "length": 1.4917500000000015, "type": "down", "log_p": 0.28678808896338337, "target": 62}, {"source": 104, "length": 2.0145, "type": "down", "log_p": 0.08942700872719002, "target": 90}, {"source": 104, "length": 2.0272500000000004, "type": "down", "log_p": 0.3772652203638436, "target": 13}, {"source": 104, "length": 1.5427499999999998, "type": "up", "log_p": 0.014992510264376023, "target": 110}, {"source": 105, "length": 2.0272500000000004, "type": "down", "log_p": 0.4615151993358275, "target": 56}, {"source": 105, "length": 2.0145, "type": "down", "log_p": 0.06924667960382608, "target": 97}, {"source": 105, "length": 1.5427499999999998, "type": "up", "log_p": 0.0, "target": 111}, {"source": 106, "length": 2.4480000000000004, "type": "down", "log_p": 0.00609901691909652, "target": 100}, {"source": 106, "length": 2.881500000000001, "type": "down", "log_p": 0.32679522505525777, "target": 2}, {"source": 106, "length": 0.6374999999999993, "type": "up", "log_p": 0.0014871516576184726, "target": 108}, {"source": 107, "length": 2.4480000000000004, "type": "down", "log_p": 0.006099016919096464, "target": 101}, {"source": 107, "length": 0.6374999999999993, "type": "up", "log_p": 0.0014871516576185262, "target": 109}, {"source": 107, "length": 2.881500000000001, "type": "down", "log_p": 0.3267952250552579, "target": 45}, {"source": 108, "length": 3.519, "type": "down", "log_p": 0.41481985811158606, "target": 8}, {"source": 108, "length": 0.6374999999999993, "type": "down", "log_p": 0.062499987561045155, "target": 106}, {"source": 108, "length": 4.7940000000000005, "type": "up", "log_p": 0.0, "target": 123}, {"source": 109, "length": 3.519, "type": "down", "log_p": 0.41481985811158606, "target": 51}, {"source": 109, "length": 0.6374999999999993, "type": "down", "log_p": 0.062499987561045287, "target": 107}, {"source": 109, "length": 4.7940000000000005, "type": "up", "log_p": 0.0, "target": 124}, {"source": 110, "length": 1.5427499999999998, "type": "down", "log_p": 0.0, "target": 104}, {"source": 110, "length": 0.2677499999999995, "type": "up", "log_p": 0.0, "target": 112}, {"source": 110, "length": 3.55725, "type": "down", "log_p": 0.0, "target": 87}, {"source": 111, "length": 1.5427499999999998, "type": "down", "log_p": 0.0, "target": 105}, {"source": 111, "length": 3.55725, "type": "down", "log_p": 0.017046739611251565, "target": 94}, {"source": 111, "length": 0.2677499999999995, "type": "up", "log_p": 0.0, "target": 113}, {"source": 112, "length": 1.7085000000000008, "type": "up", "log_p": 0.0560112152823406, "target": 114}, {"source": 112, "length": 2.3459999999999983, "type": "down", "log_p": 0.06124952787840954, "target": 102}, {"source": 112, "length": 0.2677499999999995, "type": "down", "log_p": 0.0, "target": 110}, {"source": 113, "length": 1.7085000000000008, "type": "up", "log_p": 0.0, "target": 114}, {"source": 113, "length": 2.3459999999999983, "type": "down", "log_p": 0.045999492267342304, "target": 103}, {"source": 113, "length": 0.2677499999999995, "type": "down", "log_p": 0.037341885106225256, "target": 111}, {"source": 114, "length": 1.7085000000000008, "type": "down", "log_p": 0.06770629728022828, "target": 112}, {"source": 114, "length": 1.7085000000000008, "type": "down", "log_p": 0.0, "target": 113}, {"source": 114, "length": 4.8195, "type": "up", "log_p": 0.0, "target": 147}, {"source": 115, "length": 5.6355, "type": "down", "log_p": 0.2818540031661173, "target": 16}, {"source": 115, "length": 4.60275, "type": "up", "log_p": 0.10097198861059398, "target": 145}, {"source": 115, "length": 5.62275, "type": "down", "log_p": 0.0, "target": 91}, {"source": 116, "length": 5.62275, "type": "down", "log_p": 0.0, "target": 98}, {"source": 116, "length": 5.6355, "type": "down", "log_p": 0.17647443256554418, "target": 59}, {"source": 116, "length": 4.60275, "type": "up", "log_p": 0.06391815161120011, "target": 146}, {"source": 117, "length": 6.7575, "type": "down", "log_p": 0.2865584874045015, "target": 34}, {"source": 117, "length": 1.5555000000000003, "type": "up", "log_p": 0.0, "target": 123}, {"source": 117, "length": 6.74475, "type": "down", "log_p": 0.07187409290836667, "target": 92}, {"source": 118, "length": 6.74475, "type": "down", "log_p": 0.07187409290836679, "target": 99}, {"source": 118, "length": 1.5555000000000003, "type": "up", "log_p": 0.0, "target": 124}, {"source": 118, "length": 6.7575, "type": "down", "log_p": 0.2865584874045016, "target": 77}, {"source": 119, "length": 7.777500000000001, "type": "down", "log_p": 0.10649277493506663, "target": 39}, {"source": 119, "length": 7.777500000000001, "type": "down", "log_p": 0.017386282578033384, "target": 37}, {"source": 119, "length": 0.9307499999999997, "type": "up", "log_p": 0.055600908484184516, "target": 127}, {"source": 120, "length": 7.777500000000001, "type": "down", "log_p": 0.017386282578033325, "target": 80}, {"source": 120, "length": 0.9307499999999997, "type": "up", "log_p": 0.05560090848418434, "target": 128}, {"source": 120, "length": 7.777500000000001, "type": "down", "log_p": 0.1064927749350667, "target": 82}, {"source": 121, "length": 8.16, "type": "down", "log_p": 0.019003206678761306, "target": 25}, {"source": 121, "length": 8.16, "type": "down", "log_p": 0.19135677618599106, "target": 26}, {"source": 121, "length": 0.8287500000000003, "type": "up", "log_p": 0.014009687619891062, "target": 129}, {"source": 122, "length": 0.8287500000000003, "type": "up", "log_p": 0.014009687619890932, "target": 130}, {"source": 122, "length": 8.16, "type": "down", "log_p": 0.01900320667876152, "target": 68}, {"source": 122, "length": 8.16, "type": "down", "log_p": 0.1913567761859909, "target": 69}, {"source": 123, "length": 4.7940000000000005, "type": "down", "log_p": 0.0, "target": 108}, {"source": 123, "length": 1.5555000000000003, "type": "down", "log_p": 0.0, "target": 117}, {"source": 123, "length": 0.29324999999999957, "type": "up", "log_p": 0.0, "target": 125}, {"source": 124, "length": 1.5555000000000003, "type": "down", "log_p": 0.0, "target": 118}, {"source": 124, "length": 4.7940000000000005, "type": "down", "log_p": 0.0, "target": 109}, {"source": 124, "length": 0.29324999999999957, "type": "up", "log_p": 0.0, "target": 126}, {"source": 125, "length": 0.29324999999999957, "type": "down", "log_p": 0.0, "target": 123}, {"source": 125, "length": 8.60625, "type": "down", "log_p": 0.2746789155651542, "target": 30}, {"source": 125, "length": 0.6757499999999999, "type": "up", "log_p": 0.0, "target": 135}, {"source": 126, "length": 0.6757499999999999, "type": "up", "log_p": 0.0, "target": 136}, {"source": 126, "length": 8.60625, "type": "down", "log_p": 0.2746789155651542, "target": 73}, {"source": 126, "length": 0.29324999999999957, "type": "down", "log_p": 0.0, "target": 124}, {"source": 127, "length": 0.3059999999999996, "type": "up", "log_p": 0.031047875105898015, "target": 131}, {"source": 127, "length": 8.70825, "type": "down", "log_p": 0.013088878373843912, "target": 36}, {"source": 127, "length": 0.9307499999999997, "type": "down", "log_p": 0.017600928009419953, "target": 119}, {"source": 128, "length": 0.9307499999999997, "type": "down", "log_p": 0.01760092800941968, "target": 120}, {"source": 128, "length": 0.3059999999999996, "type": "up", "log_p": 0.031047875105897984, "target": 132}, {"source": 128, "length": 8.70825, "type": "down", "log_p": 0.013088878373844245, "target": 79}, {"source": 129, "length": 8.98875, "type": "down", "log_p": 0.06589752778080753, "target": 24}, {"source": 129, "length": 0.8287500000000003, "type": "down", "log_p": 0.0, "target": 121}, {"source": 129, "length": 0.5737499999999995, "type": "up", "log_p": 0.04162508053142056, "target": 139}, {"source": 130, "length": 0.8287500000000003, "type": "down", "log_p": 0.0, "target": 122}, {"source": 130, "length": 8.98875, "type": "down", "log_p": 0.06589752778080767, "target": 67}, {"source": 130, "length": 0.5737499999999995, "type": "up", "log_p": 0.04162508053142063, "target": 140}, {"source": 131, "length": 1.0455, "type": "up", "log_p": 0.24603824122166829, "target": 141}, {"source": 131, "length": 9.01425, "type": "down", "log_p": 0.05021450850306193, "target": 38}, {"source": 131, "length": 0.3059999999999996, "type": "down", "log_p": 0.008582292589850462, "target": 127}, {"source": 132, "length": 0.3059999999999996, "type": "down", "log_p": 0.0085822925898505, "target": 128}, {"source": 132, "length": 9.01425, "type": "down", "log_p": 0.05021450850306204, "target": 81}, {"source": 132, "length": 1.0455, "type": "up", "log_p": 0.24604103136310496, "target": 142}, {"source": 133, "length": 9.0525, "type": "down", "log_p": 0.10565884629537316, "target": 23}, {"source": 133, "length": 9.0525, "type": "down", "log_p": 0.16345422767570567, "target": 29}, {"source": 133, "length": 1.0964999999999998, "type": "up", "log_p": 0.09116401490577164, "target": 143}, {"source": 134, "length": 9.0525, "type": "down", "log_p": 0.16345422767570567, "target": 72}, {"source": 134, "length": 1.0964999999999998, "type": "up", "log_p": 0.0911640149057718, "target": 144}, {"source": 134, "length": 9.0525, "type": "down", "log_p": 0.10565884629537321, "target": 66}, {"source": 135, "length": 9.282, "type": "down", "log_p": 0.36058632477771196, "target": 33}, {"source": 135, "length": 2.1675, "type": "up", "log_p": 0.09939166712796485, "target": 148}, {"source": 135, "length": 0.6757499999999999, "type": "down", "log_p": 0.07674665868229552, "target": 125}, {"source": 136, "length": 9.282, "type": "down", "log_p": 0.36058632477771213, "target": 76}, {"source": 136, "length": 2.1675, "type": "up", "log_p": 0.0993916671279647, "target": 149}, {"source": 136, "length": 0.6757499999999999, "type": "down", "log_p": 0.07674665868229535, "target": 126}, {"source": 137, "length": 9.42225, "type": "down", "log_p": 0.012922303806525356, "target": 27}, {"source": 137, "length": 9.42225, "type": "down", "log_p": 0.1005171933114871, "target": 28}, {"source": 137, "length": 0.14024999999999999, "type": "up", "log_p": 0.009407446414937633, "target": 139}, {"source": 138, "length": 0.14024999999999999, "type": "up", "log_p": 0.009407446414937563, "target": 140}, {"source": 138, "length": 9.42225, "type": "down", "log_p": 0.012922303806525245, "target": 70}, {"source": 138, "length": 9.42225, "type": "down", "log_p": 0.10051719331148722, "target": 71}, {"source": 139, "length": 0.14024999999999999, "type": "down", "log_p": 0.09819488899460889, "target": 137}, {"source": 139, "length": 0.5737499999999995, "type": "down", "log_p": 0.0, "target": 129}, {"source": 139, "length": 0.5865, "type": "up", "log_p": 0.08372906119491934, "target": 143}, {"source": 140, "length": 0.5865, "type": "up", "log_p": 0.08372906119491914, "target": 144}, {"source": 140, "length": 0.5737499999999995, "type": "down", "log_p": 0.0, "target": 130}, {"source": 140, "length": 0.14024999999999999, "type": "down", "log_p": 0.09819488899460882, "target": 138}, {"source": 141, "length": 10.047, "type": "down", "log_p": 0.0, "target": 88}, {"source": 141, "length": 1.0455, "type": "down", "log_p": 0.3017055987342464, "target": 131}, {"source": 141, "length": 1.734, "type": "up", "log_p": 0.0, "target": 150}, {"source": 142, "length": 10.047, "type": "down", "log_p": 0.0, "target": 95}, {"source": 142, "length": 1.0455, "type": "down", "log_p": 0.3017028085928096, "target": 132}, {"source": 142, "length": 1.734, "type": "up", "log_p": 0.0, "target": 151}, {"source": 143, "length": 0.5865, "type": "down", "log_p": 0.025045278882508307, "target": 139}, {"source": 143, "length": 1.3005, "type": "up", "log_p": 0.08048579573057206, "target": 148}, {"source": 143, "length": 1.0964999999999998, "type": "down", "log_p": 0.03211636903274322, "target": 133}, {"source": 144, "length": 0.5865, "type": "down", "log_p": 0.025045278882508223, "target": 140}, {"source": 144, "length": 1.3005, "type": "up", "log_p": 0.0804857957305721, "target": 149}, {"source": 144, "length": 1.0964999999999998, "type": "down", "log_p": 0.0321163690327433, "target": 134}, {"source": 145, "length": 10.2255, "type": "down", "log_p": 0.0, "target": 89}, {"source": 145, "length": 4.60275, "type": "down", "log_p": 0.1120142892036988, "target": 115}, {"source": 145, "length": 0.12749999999999995, "type": "up", "log_p": 0.03487378920898491, "target": 147}, {"source": 146, "length": 10.2255, "type": "down", "log_p": 0.0, "target": 96}, {"source": 146, "length": 2.5117499999999997, "type": "up", "log_p": 0.0045943702616546706, "target": 152}, {"source": 146, "length": 4.60275, "type": "down", "log_p": 0.038349844306694594, "target": 116}, {"source": 147, "length": 2.3842499999999998, "type": "up", "log_p": 0.03604117289904206, "target": 152}, {"source": 147, "length": 0.12749999999999995, "type": "down", "log_p": 0.06005879890042344, "target": 145}, {"source": 147, "length": 4.8195, "type": "down", "log_p": 0.0, "target": 114}, {"source": 148, "length": 2.1675, "type": "down", "log_p": 0.0, "target": 135}, {"source": 148, "length": 0.34425000000000006, "type": "up", "log_p": 0.03990640484014886, "target": 150}, {"source": 148, "length": 1.3005, "type": "down", "log_p": 0.10686494308609674, "target": 143}, {"source": 149, "length": 2.1675, "type": "down", "log_p": 0.0, "target": 136}, {"source": 149, "length": 1.3005, "type": "down", "log_p": 0.10686494308609672, "target": 144}, {"source": 149, "length": 0.34425000000000006, "type": "up", "log_p": 0.03991647421553762, "target": 151}, {"source": 150, "length": 0.9562499999999999, "type": "up", "log_p": 0.025931986171508936, "target": 152}, {"source": 150, "length": 0.34425000000000006, "type": "down", "log_p": 0.0, "target": 148}, {"source": 150, "length": 1.734, "type": "down", "log_p": 0.03831983085445374, "target": 141}, {"source": 151, "length": 0.9562499999999999, "type": "up", "log_p": 0.021589863080875453, "target": 152}, {"source": 151, "length": 0.34425000000000006, "type": "down", "log_p": 0.0, "target": 149}, {"source": 151, "length": 1.734, "type": "down", "log_p": 0.038333620431673605, "target": 142}, {"source": 152, "length": 2.5117499999999997, "type": "down", "log_p": 0.09930654822083936, "target": 146}, {"source": 152, "length": 2.3842499999999998, "type": "down", "log_p": 0.0283598338019282, "target": 147}, {"source": 152, "length": 0.9562499999999999, "type": "down", "log_p": 0.034379727409510175, "target": 150}, {"source": 152, "length": 0.9562499999999999, "type": "down", "log_p": 0.03071074694461876, "target": 151}], "multigraph": false}